[{"name":"75","type":"scroll","ts":1758253526865,"meta":{"type":"scroll","name":"75","meta":{"sessionId":"sess_1758238778359_mb1z62ybv","utm":{"utm_source":null,"utm_medium":null,"utm_campaign":null,"utm_term":null,"utm_content":null},"path":"/murray","referrer":"","timestamp":1758253526152,"userAgent":"Mozilla/5.0 (Windows NT 10.0; Win64; x64) AppleWebKit/537.36 (KHTML, like Gecko) Chrome/140.0.0.0 Safari/537.36"}}},{"name":"75","type":"scroll","ts":1758253526902,"meta":{"type":"scroll","name":"75","meta":{"sessionId":"sess_1758238778359_mb1z62ybv","utm":{"utm_source":null,"utm_medium":null,"utm_campaign":null,"utm_term":null,"utm_content":null},"path":"/murray","referrer":"","timestamp":1758253526204,"userAgent":"Mozilla/5.0 (Windows NT 10.0; Win64; x64) AppleWebKit/537.36 (KHTML, like Gecko) Chrome/140.0.0.0 Safari/537.36"}}}]