[{"name":"50","type":"scroll","ts":1756362693432,"meta":{"type":"scroll","name":"50"}},{"name":"50","type":"scroll","ts":1756362693832,"meta":{"type":"scroll","name":"50"}},{"name":"50","type":"scroll","ts":1756362694154,"meta":{"type":"scroll","name":"50"}},{"name":"75","type":"scroll","ts":1756362694191,"meta":{"type":"scroll","name":"75"}},{"name":"75","type":"scroll","ts":1756362698617,"meta":{"type":"scroll","name":"75"}},{"name":"90","type":"scroll","ts":1756362699455,"meta":{"type":"scroll","name":"90"}},{"name":"90","type":"scroll","ts":1756362700963,"meta":{"type":"scroll","name":"90"}}]